emotional_detection/__init__.py
emotional_detection/main.py
emotional_detection-0.1.3.dist-info/WHEEL
emotional_detection-0.1.3.dist-info/METADATA
emotional_detection-0.1.3.dist-info/RECORD
